xyzcad/__init__.py
xyzcad/_version.py
xyzcad/export.py
xyzcad/render.py
xyzcad/tlt.py
xyzcad-0.7.1.dist-info/LICENSE
xyzcad-0.7.1.dist-info/METADATA
xyzcad-0.7.1.dist-info/WHEEL
xyzcad-0.7.1.dist-info/RECORD
