Metadata-Version: 2.3
Name: xyzcad
Version: 0.7.1
Summary: An implicit surface based functional CAD system
License: AGPLv3
Author: Stefan Helmert
Author-email: stefan.helmert@t-online.de
Requires-Python: >=3.11,<4.0
Classifier: License :: Other/Proprietary License
Classifier: Programming Language :: Python :: 3
Classifier: Programming Language :: Python :: 3.11
Classifier: Programming Language :: Python :: 3.12
Classifier: Programming Language :: Python :: 3.13
Requires-Dist: numba (>=0.61.2,<0.62.0)
Requires-Dist: numpy (>=2.2.0,<3.0.0)
Requires-Dist: numpy-stl (>=3.1.1,<4.0.0)
